al_bday_enigma/__main__.py
al_bday_enigma-0.1.0.dist-info/WHEEL
al_bday_enigma-0.1.0.dist-info/METADATA
al_bday_enigma-0.1.0.dist-info/RECORD
