Metadata-Version: 2.1
Name: al-bday-enigma
Version: 0.1.0
Summary: 
License: AGPL-3.0-or-later
Author: Stefano Pigozzi
Author-email: ste.pigozzi@gmail.com
Requires-Python: >=3.8,<4.0
Classifier: License :: OSI Approved :: GNU Affero General Public License v3 or later (AGPLv3+)
Classifier: Programming Language :: Python :: 3
Classifier: Programming Language :: Python :: 3.8
Requires-Dist: fastapi (>=0.62.0,<0.63.0)
Requires-Dist: royalnet (==6.0.0a16)
Requires-Dist: uvicorn (>=0.12.3,<0.13.0)
